MANIFEST.in
README.txt
__init__.py
ado_consts.py
adodbapi.py
apibase.py
is64bit.py
license.txt
older_whatsnew.txt
process_connect_string.py
quick_reference.md
remote.py
schema_table.py
setup.cfg
setup.py
adodbapi.egg-info/PKG-INFO
adodbapi.egg-info/SOURCES.txt
adodbapi.egg-info/dependency_links.txt
adodbapi.egg-info/not-zip-safe
adodbapi.egg-info/top_level.txt
examples/db_print.py
examples/db_print_simple.py
examples/db_table_names.py
examples/remote_xls_read.py
examples/run_server_py_25.py
examples/test.mdb
examples/xls_read.py
examples/xls_write.py
remote/adodbapi_service.py
remote/remote.md
remote/server.py
test/adodbapitest.py
test/adodbapitestconfig.py
test/build3test.bat
test/dbapi20.py
test/is64bit.py
test/runtests.bat
test/setuptestframework.py
test/startserver.bat
test/test_adodbapi_dbapi20.py
test/tryconnection.py