Metadata-Version: 2.1
Name: adodbapi
Version: 2.6.2.0
Summary: A pure Python package implementing PEP 249 DB-API using Microsoft ADO.
Home-page: http://sourceforge.net/projects/adodbapi
Author: Henrik Ekelund, Vernon Cole, et.al.
Author-email: vernondcole@gmail.com
Maintainer: Vernon Cole
Maintainer-email: vernondcole@gmail.com
License: LGPL
Keywords: database ado odbc dbapi db-api Microsoft SQL
Platform: Windows
Classifier: Development Status :: 5 - Production/Stable
Classifier: Intended Audience :: Developers
Classifier: License :: OSI Approved :: GNU Library or Lesser General Public License (LGPL)
Classifier: Operating System :: Microsoft :: Windows
Classifier: Operating System :: POSIX :: Linux
Classifier: Programming Language :: Python
Classifier: Programming Language :: Python :: 3
Classifier: Programming Language :: SQL
Classifier: Topic :: Software Development
Classifier: Topic :: Software Development :: Libraries :: Python Modules
Classifier: Topic :: Database
